MODISCI/MODISCI.py
MODISCI/__init__.py
MODISCI/version.py
modisci-1.4.0.dist-info/licenses/LICENSE
tests/test_import_MODISCI.py
tests/test_import_dependencies.py
modisci-1.4.0.dist-info/METADATA
modisci-1.4.0.dist-info/WHEEL
modisci-1.4.0.dist-info/top_level.txt
modisci-1.4.0.dist-info/RECORD
