Metadata-Version: 2.4
Name: MODISCI
Version: 1.4.0
Summary: generates rasters of MODIS clumping index
Author-email: "Gregory H. Halverson" <gregory.h.halverson@jpl.nasa.gov>
Project-URL: Homepage, https://github.com/JPL-Evapotranspiration-Algorithms/MODISCI
Classifier: Programming Language :: Python :: 3
Classifier: Operating System :: OS Independent
Requires-Python: >=3.10
License-File: LICENSE
Requires-Dist: ECOv002-calval-tables>=1.6.0
Requires-Dist: colored_logging
Requires-Dist: rasters>=1.9.0
Dynamic: license-file
